atlisp_ole/__init__.py
atlisp_ole/__main__.py
atlisp_ole/atlisp-ole.py
atlisp_ole/atlisp-ole.spec
atlisp_ole/atlisp_ole.py
atlisp_ole-0.2.7.dist-info/METADATA
atlisp_ole-0.2.7.dist-info/WHEEL
atlisp_ole-0.2.7.dist-info/entry_points.txt
atlisp_ole-0.2.7.dist-info/licenses/LICENSE
atlisp_ole-0.2.7.dist-info/RECORD
