Metadata-Version: 2.4
Name: atlisp-ole
Version: 0.2.7
Summary: atlisp-ole 是 @lisp CAD应用云调用py将图片以OLE方式插入dwgr的应用包。
Project-URL: Homepage, https://atlisp.cn
Author-email: VitalGG <vitalgg@gmail.com>
License: MIT License
License-File: LICENSE
Keywords: @lisp,CAD应用云,atlisp,autolisp
Classifier: License :: OSI Approved :: MIT License
Classifier: Operating System :: OS Independent
Classifier: Programming Language :: Python :: 3
Requires-Python: >=3.7
Requires-Dist: atlisp
Requires-Dist: pillow
Requires-Dist: pywin32>280
